ht_text_prep/__init__.py
ht_text_prep/htrc/__init__.py
ht_text_prep/htrc/models.py
ht_text_prep/htrc/runningheaders.py
ht_text_prep/htrc/tests.py
ht_text_prep/htrc/utils.py
ht_text_prep-1.2.dist-info/LICENSE
ht_text_prep-1.2.dist-info/METADATA
ht_text_prep-1.2.dist-info/WHEEL
ht_text_prep-1.2.dist-info/top_level.txt
ht_text_prep-1.2.dist-info/RECORD
