Metadata-Version: 2.1
Name: ht-text-prep
Version: 1.2
Summary: Text processing and analysis for HathiTrust Research Center
Home-page: https://github.com/htrc/ht-text-prep
Author: Ashan Liyanage, Ryan Dubnicek, Daniel J. Evans, Yuerong Hu, Elizabeth R. Schwartz
Author-email: rdubnic2@illinois.edu
Classifier: Programming Language :: Python :: 3
Classifier: License :: OSI Approved :: University of Illinois/NCSA Open Source License
Classifier: Operating System :: OS Independent
Requires-Python: >=3.6
License-File: LICENSE
